fastsdk/__init__.py
fastsdk/fastClient.py
fastsdk/fastSDK.py
fastsdk/service_definition.py
fastsdk/utils.py
fastsdk/sdk_factory/__init__.py
fastsdk/sdk_factory/sdk_factory.py
fastsdk/sdk_factory/sdk_template.j2
fastsdk/service_interaction/__init__.py
fastsdk/service_interaction/api_job_manager.py
fastsdk/service_interaction/request/__init__.py
fastsdk/service_interaction/request/api_client.py
fastsdk/service_interaction/request/api_client_replicate.py
fastsdk/service_interaction/request/api_client_runpod.py
fastsdk/service_interaction/request/api_client_socaity.py
fastsdk/service_interaction/request/file_handler.py
fastsdk/service_interaction/response/api_job_status.py
fastsdk/service_interaction/response/base_response.py
fastsdk/service_interaction/response/response_parser.py
fastsdk/service_interaction/response/response_parser_strategies.py
fastsdk/service_management/__init__.py
fastsdk/service_management/service_manager.py
fastsdk/service_management/service_store/FileSystemStore.py
fastsdk/service_management/service_store/IServiceStore.py
fastsdk/service_management/service_store/__init__.py
fastsdk/service_specification_loader/runpod_open_api_loader.py
fastsdk/service_specification_loader/spec_loader.py
fastsdk/service_specification_loader/parsers/__init__.py
fastsdk/service_specification_loader/parsers/base_parser.py
fastsdk/service_specification_loader/parsers/factory.py
fastsdk/service_specification_loader/parsers/fasttaskapi_parser.py
fastsdk/service_specification_loader/parsers/openapi_parser.py
fastsdk/service_specification_loader/parsers/parser.py
fastsdk/service_specification_loader/parsers/service_adress_parser.py
fastsdk/service_specification_loader/parsers/cog/cog_parser.py
fastsdk/service_specification_loader/parsers/cog/cog_parser2.py
fastsdk-0.2.14.dist-info/licenses/LICENSE
fastsdk-0.2.14.dist-info/METADATA
fastsdk-0.2.14.dist-info/WHEEL
fastsdk-0.2.14.dist-info/top_level.txt
fastsdk-0.2.14.dist-info/RECORD
