Metadata-Version: 2.4
Name: fastsdk
Version: 0.2.14
Summary: Your SDK and model zoo for generative AI. Build AI-powered applications with ease.
Author: SocAIty
License:                     GNU GENERAL PUBLIC LICENSE
Project-URL: Repository, https://github.com/SocAIty/fastsdk
Project-URL: Homepage, https://www.socaity.ai
Requires-Python: >=3.8
License-File: LICENSE
Requires-Dist: httpx
Requires-Dist: tqdm
Requires-Dist: pydantic>=2.11.3
Requires-Dist: meseex>=0.0.5
Requires-Dist: media-toolkit>=00.02.21
Requires-Dist: singleton_decorator==1.0.0
Requires-Dist: jinja2>=3.1.6
Requires-Dist: fastcloud>=0.0.13
Provides-Extra: dev
Requires-Dist: pytest; extra == "dev"
Dynamic: license-file
